cfn_visualizer/__init__.py
cfn_visualizer/__main__.py
cfn_visualizer/exceptions.py
cfn_visualizer/utils.py
cfn_visualizer/visualizer.py
aws_cloudformation_visualizer-0.0.3.dist-info/METADATA
aws_cloudformation_visualizer-0.0.3.dist-info/WHEEL
aws_cloudformation_visualizer-0.0.3.dist-info/top_level.txt
aws_cloudformation_visualizer-0.0.3.dist-info/RECORD
